agno_cli/__init__.py
agno_cli/cli.py
agno_cli/agents/__init__.py
agno_cli/agents/agent_state.py
agno_cli/agents/multi_agent.py
agno_cli/agents/orchestrator.py
agno_cli/commands/__init__.py
agno_cli/commands/agent_commands.py
agno_cli/commands/chat_commands.py
agno_cli/commands/metrics_commands.py
agno_cli/commands/team_commands.py
agno_cli/commands/tool_commands.py
agno_cli/commands/trace_commands.py
agno_cli/core/__init__.py
agno_cli/core/agent.py
agno_cli/core/config.py
agno_cli/core/session.py
agno_cli/reasoning/__init__.py
agno_cli/reasoning/metrics.py
agno_cli/reasoning/tracer.py
agno_cli/tools/__init__.py
agno_cli/tools/arxiv_tools.py
agno_cli/tools/crawl4ai_tools.py
agno_cli/tools/csv_tools.py
agno_cli/tools/docker_tools.py
agno_cli/tools/duckdb_tools.py
agno_cli/tools/file_system_tools.py
agno_cli/tools/financial_tools.py
agno_cli/tools/function_tools.py
agno_cli/tools/hackernews_tools.py
agno_cli/tools/math_tools.py
agno_cli/tools/models_tools.py
agno_cli/tools/openai_tools.py
agno_cli/tools/opencv_tools.py
agno_cli/tools/pandas_tools.py
agno_cli/tools/postgres_tools.py
agno_cli/tools/pubmed_tools.py
agno_cli/tools/screenshot_tools.py
agno_cli/tools/search_tools.py
agno_cli/tools/shell_tools.py
agno_cli/tools/sleep_tools.py
agno_cli/tools/sql_tools.py
agno_cli/tools/thinking_tools.py
agno_cli/tools/visualization_tools.py
agno_cli/tools/wikipedia_tools.py
agno_cli/utils/__init__.py
agno_cli/utils/helpers.py
agno_cli/utils/logging.py
agno_cli-2.4.10.dist-info/licenses/LICENSE
agno_cli-2.4.10.dist-info/METADATA
agno_cli-2.4.10.dist-info/WHEEL
agno_cli-2.4.10.dist-info/entry_points.txt
agno_cli-2.4.10.dist-info/top_level.txt
agno_cli-2.4.10.dist-info/RECORD
