Metadata-Version: 2.4
Name: agno-cli
Version: 2.4.10
Summary: Enhanced Agno CLI - Multi-Agent Terminal Assistant with Advanced Reasoning and Tool Integration
Home-page: https://github.com/paulgg-code/agno-cli
Author: Paul Gedeon
License: MIT
Project-URL: Homepage, https://github.com/paulgg-code/agno-cli
Project-URL: Repository, https://github.com/paulgg-code/agno-cli
Project-URL: Issues, https://github.com/paulgg-code/agno-cli/issues
Project-URL: Changelog, https://github.com/paulgg-code/agno-cli/blob/main/CHANGELOG.md
Keywords: ai,cli,agents,multi-agent,reasoning,terminal,assistant
Classifier: Development Status :: 4 - Beta
Classifier: Intended Audience :: Developers
Classifier: License :: OSI Approved :: MIT License
Classifier: Operating System :: OS Independent
Classifier: Programming Language :: Python :: 3
Classifier: Programming Language :: Python :: 3.8
Classifier: Programming Language :: Python :: 3.9
Classifier: Programming Language :: Python :: 3.10
Classifier: Programming Language :: Python :: 3.11
Classifier: Programming Language :: Python :: 3.12
Classifier: Topic :: Scientific/Engineering :: Artificial Intelligence
Classifier: Topic :: Software Development :: Libraries :: Python Modules
Classifier: Topic :: System :: Shells
Classifier: Topic :: Utilities
Requires-Python: >=3.8
License-File: LICENSE
Requires-Dist: agno>=0.1.0
Requires-Dist: typer[all]>=0.9.0
Requires-Dist: rich>=13.0.0
Requires-Dist: pyyaml>=6.0
Requires-Dist: requests>=2.28.0
Requires-Dist: pandas>=1.5.0
Requires-Dist: numpy>=1.21.0
Provides-Extra: search
Requires-Dist: duckduckgo-search>=3.8.0; extra == "search"
Requires-Dist: googlesearch-python>=1.2.0; extra == "search"
Requires-Dist: beautifulsoup4>=4.11.0; extra == "search"
Provides-Extra: fintech
Requires-Dist: yfinance>=0.2.0; extra == "fintech"
Requires-Dist: matplotlib>=3.6.0; extra == "fintech"
Requires-Dist: seaborn>=0.12.0; extra == "fintech"
Requires-Dist: plotly>=5.15.0; extra == "fintech"
Provides-Extra: math
Requires-Dist: sympy>=1.11.0; extra == "math"
Requires-Dist: scipy>=1.9.0; extra == "math"
Requires-Dist: scikit-learn>=1.2.0; extra == "math"
Requires-Dist: openpyxl>=3.0.0; extra == "math"
Provides-Extra: comm
Requires-Dist: slack-sdk>=3.20.0; extra == "comm"
Requires-Dist: discord.py>=2.2.0; extra == "comm"
Requires-Dist: python-telegram-bot>=20.0; extra == "comm"
Requires-Dist: twilio>=8.0.0; extra == "comm"
Requires-Dist: sendgrid>=6.10.0; extra == "comm"
Requires-Dist: PyGithub>=1.58.0; extra == "comm"
Provides-Extra: media
Requires-Dist: pillow>=9.5.0; extra == "media"
Requires-Dist: opencv-python>=4.7.0; extra == "media"
Requires-Dist: moviepy>=1.0.3; extra == "media"
Requires-Dist: matplotlib>=3.6.0; extra == "media"
Requires-Dist: plotly>=5.15.0; extra == "media"
Provides-Extra: knowledge
Requires-Dist: wikipedia>=1.4.0; extra == "knowledge"
Requires-Dist: arxiv>=1.4.0; extra == "knowledge"
Requires-Dist: feedparser>=6.0.0; extra == "knowledge"
Provides-Extra: dev
Requires-Dist: pytest>=7.0.0; extra == "dev"
Requires-Dist: pytest-cov>=4.0.0; extra == "dev"
Requires-Dist: black>=23.0.0; extra == "dev"
Requires-Dist: flake8>=6.0.0; extra == "dev"
Requires-Dist: mypy>=1.0.0; extra == "dev"
Requires-Dist: pre-commit>=3.0.0; extra == "dev"
Provides-Extra: all
Requires-Dist: agno-cli[comm,dev,fintech,knowledge,math,media,search]; extra == "all"
Dynamic: home-page
Dynamic: license-file
Dynamic: requires-python
